airflow_dbt_cta/__init__.py
airflow_dbt_cta/__version__.py
airflow_dbt_cta/hooks/__init__.py
airflow_dbt_cta/hooks/dbt_hook.py
airflow_dbt_cta/operators/__init__.py
airflow_dbt_cta/operators/dbt_operator.py
airflow_dbt_cta-0.0.6.dist-info/LICENSE.txt
airflow_dbt_cta-0.0.6.dist-info/METADATA
airflow_dbt_cta-0.0.6.dist-info/WHEEL
airflow_dbt_cta-0.0.6.dist-info/top_level.txt
airflow_dbt_cta-0.0.6.dist-info/RECORD
