Metadata-Version: 2.1
Name: airflow-dbt-cta
Version: 0.0.6
Summary: Apache Airflow integration for dbt (forked from https://github.com/gocardless/airflow-dbt)
Home-page: https://github.com/communitytechalliance/airflow-dbt
Author: GoCardless
Author-email: engineering@gocardless.com
License: MIT
Classifier: Development Status :: 5 - Production/Stable
Classifier: License :: OSI Approved :: MIT License
Classifier: Operating System :: MacOS :: MacOS X
Classifier: Operating System :: POSIX :: Linux
Classifier: Programming Language :: Python :: 3.7
License-File: LICENSE.txt
Requires-Dist: apache-airflow (>=1.10.3)
